pylarm/__init__.py
pylarm/_utils.py
pylarm/alarm_clock.py
pylarm-2.1.dist-info/METADATA
pylarm-2.1.dist-info/WHEEL
pylarm-2.1.dist-info/entry_points.txt
pylarm-2.1.dist-info/top_level.txt
pylarm-2.1.dist-info/RECORD
