Metadata-Version: 2.1
Name: pylarm
Version: 2.1
Summary: Minimalistic tool to set alarms from the terminal.
Home-page: UNKNOWN
Author: francisco-simoes
Author-email: francisconfqsimoes@gmail.com
License: UNKNOWN
Platform: UNKNOWN
Classifier: Programming Language :: Python :: 3
Classifier: License :: OSI Approved :: MIT License
Classifier: Operating System :: OS Independent
Requires-Python: >=3.9
Requires-Dist: click (==8.1.3)
Requires-Dist: colorama (==0.4.6)
Requires-Dist: pipfile (==0.0.2)
Requires-Dist: playsound (==1.3.0)
Requires-Dist: pretty-errors (==1.2.25)
Requires-Dist: psutil (==5.9.4)
Requires-Dist: toml (==0.10.2)
